plex_assets_manager/Movie.py
plex_assets_manager/PlexMovieLib.py
plex_assets_manager/__init__.py
plex_assets_manager/__main__.py
plex_assets_manager/conf.py
plex_assets_manager/main.py
plex_assets_manager/utils.py
plex_assets_manager-0.1.1.dist-info/LICENSE
plex_assets_manager-0.1.1.dist-info/METADATA
plex_assets_manager-0.1.1.dist-info/WHEEL
plex_assets_manager-0.1.1.dist-info/entry_points.txt
plex_assets_manager-0.1.1.dist-info/top_level.txt
plex_assets_manager-0.1.1.dist-info/RECORD
