Metadata-Version: 2.1
Name: plex-assets-manager
Version: 0.1.1
Summary: A Python project for managing and organizing Plex media library
Home-page: https://github.com/yourusername/plex_extension
Author: Kiritee Konark Mishra
Author-email: konark@gmail.com
Classifier: Programming Language :: Python :: 3.11
Classifier: License :: OSI Approved :: MIT License
Classifier: Operating System :: OS Independent
Requires-Python: >=3.11
License-File: LICENSE
Requires-Dist: plexapi
Requires-Dist: cinemagoer
Requires-Dist: yt-dlp
Requires-Dist: phantomjs
Requires-Dist: argparse
Requires-Dist: python-dotenv
